README.rst
_fif.pyx
fif.cxx
setup.cfg
setup.py
version.py
py_fif.egg-info/PKG-INFO
py_fif.egg-info/SOURCES.txt
py_fif.egg-info/dependency_links.txt
py_fif.egg-info/requires.txt
py_fif.egg-info/top_level.txt