Metadata-Version: 2.1
Name: py-fif
Version: 1.0.2
Summary: Functional Isolation Forest
Home-page: https://github.com/GuillaumeStaermanML/FIF
Author: Guillaume Staerman
Author-email: guillaume.staerman@telecom-paris.fr
License: License.txt
Download-URL: https://github.com/GuillaumeStaermanML/FIF/archive/refs/tags/1.0.2.tar.gz
Platform: UNKNOWN
